{
    "data": {
        "count": 500,
        "list": [{
            "cause_step_1_num_ul_rate": "100.0%",
            "Location_latitude": 30.24631068,
            "single_pass_call_num_rate": "0.0%",
            "Worse_Quality_call_num_rate": "100.0%",
            "cause_step_1_num_dl_rate": null,
            "Worse_Quality_time_rate_DL": null,
            "slice_total_count_UL": 2,
            "local_city": "杭州",
            "Worse_Quality_call_num": 1,
            "Worse_MOS_call_num": 1,
            "Worse_Quality_time_rate_UL": "100.0%",
            "Worse_Quality_time_rate": "100.0%",
            "slice_total_count_DL": 0,
            "call_num": 1,
            "Worse_Quality_time": 10.0430000000000000,
            "call_time": 10.0430000000000000,
            "Worse_Quality_slice_count_UL": 2,
            "cause_null_main_coverage_slice_num_rate": "0.0%",
            "cause_mod3_conflict_slice_num_rate": "0.0%",
            "Start_Time": "2021-03-21 00:00:00",
            "rtp_packet_loss_num_UL_rate": "0.9%",
            "Location_longitude": 120.154492,
            "Freq": 1300,
            "Worse_Quality_slice_count": 2,
            "District": "上城区",
            "MOS_UL": 2.5,
            "color": 1,
            "slice_total_count": 2,
            "Cause_Radio_RSRP_DL_slice_num_rate": "0.0%",
            "Cause_Radio_RSRQ_UL_slice_num_rate": "0.0%",
            "End_Time": "2021-03-21 23:59:59",
            "Worse_Quality_slice_count_DL": 0,
            "pci": 52,
            "cause_ul_dl_unbalance_slice_num_rate": "0.0%",
            "radio_problem_slice_num_rate": "0.0%",
            "single_pass_call_num": 0,
            "rtp_packet_loss_num_DL_rate": null,
            "cause_neighbour_cell_loss_slice_num_rate": "0.0%",
            "Cause_Radio_RSRP_UL_slice_num_rate": "0.0%",
            "RTCP_ring_delay_UL": 188.5,
            "Worse_MOS_call_num_rate": "100.0%",
            "Cause_Radio_RSRQ_DL_slice_num_rate": "0.0%",
            "ECI": 153299330,
            "Call_Type": "全部",
            "cell_Name": "杭州东篱会所FDD1800_130",
            "Freq_band": "FDD-1800",
            "MOS_DL": null,
            "RTCP_ring_delay_DL": null,
            "radio_problem_mr_num": 0,
            "cause_overlap_coverage_slice_num_rate": "0.0%",
            "radio_problem_slice_num": 0
        }, {
            "cause_step_1_num_ul_rate": "100.0%",
            "Location_latitude": 30.229806,
            "single_pass_call_num_rate": "0.0%",
            "Worse_Quality_call_num_rate": "100.0%",
            "cause_step_1_num_dl_rate": null,
            "Worse_Quality_time_rate_DL": null,
            "slice_total_count_UL": 1,
            "local_city": "杭州",
            "Worse_Quality_call_num": 1,
            "Worse_MOS_call_num": 1,
            "Worse_Quality_time_rate_UL": "100.0%",
            "Worse_Quality_time_rate": "100.0%",
            "slice_total_count_DL": 0,
            "call_num": 1,
            "Worse_Quality_time": 10.5970000000000000,
            "call_time": 10.5970000000000000,
            "Worse_Quality_slice_count_UL": 1,
            "cause_null_main_coverage_slice_num_rate": "0.0%",
            "cause_mod3_conflict_slice_num_rate": "0.0%",
            "Start_Time": "2021-03-29 00:00:00",
            "rtp_packet_loss_num_UL_rate": "50.0%",
            "Location_longitude": 120.228993,
            "Freq": 38950,
            "Worse_Quality_slice_count": 1,
            "District": "滨江区",
            "MOS_UL": 1.9,
            "color": 1,
            "slice_total_count": 1,
            "Cause_Radio_RSRP_DL_slice_num_rate": "0.0%",
            "Cause_Radio_RSRQ_UL_slice_num_rate": "0.0%",
            "End_Time": "2021-03-29 23:59:59",
            "Worse_Quality_slice_count_DL": 0,
            "pci": 133,
            "cause_ul_dl_unbalance_slice_num_rate": "0.0%",
            "radio_problem_slice_num_rate": "0.0%",
            "single_pass_call_num": 0,
            "rtp_packet_loss_num_DL_rate": null,
            "cause_neighbour_cell_loss_slice_num_rate": "0.0%",
            "Cause_Radio_RSRP_UL_slice_num_rate": "0.0%",
            "RTCP_ring_delay_UL": 0.0,
            "Worse_MOS_call_num_rate": "100.0%",
            "Cause_Radio_RSRQ_DL_slice_num_rate": "0.0%",
            "ECI": 210674754,
            "Call_Type": "全部",
            "cell_Name": "杭州奥体网球中心决赛馆B1F东面及1F南面SF_66",
            "Freq_band": "E1",
            "MOS_DL": null,
            "RTCP_ring_delay_DL": null,
            "radio_problem_mr_num": 0,
            "cause_overlap_coverage_slice_num_rate": "0.0%",
            "radio_problem_slice_num": 0
        }, {
            "cause_step_1_num_ul_rate": "102.1%",
            "Location_latitude": 30.211352,
            "single_pass_call_num_rate": "0.0%",
            "Worse_Quality_call_num_rate": "25.0%",
            "cause_step_1_num_dl_rate": "98.7%",
            "Worse_Quality_time_rate_DL": "72.8%",
            "slice_total_count_UL": 74,
            "local_city": "杭州",
            "Worse_Quality_call_num": 2,
            "Worse_MOS_call_num": 2,
            "Worse_Quality_time_rate_UL": "71.6%",
            "Worse_Quality_time_rate": "73.4%",
            "slice_total_count_DL": 103,
            "call_num": 8,
            "Worse_Quality_time": 496.3500000000000000,
            "call_time": 676.1530000000000000,
            "Worse_Quality_slice_count_UL": 48,
            "cause_null_main_coverage_slice_num_rate": "0.0%",
            "cause_mod3_conflict_slice_num_rate": "0.0%",
            "Start_Time": "2021-03-18 00:00:00",
            "rtp_packet_loss_num_UL_rate": "16.5%",
            "Location_longitude": 120.214267,
            "Freq": 38950,
            "Worse_Quality_slice_count": 125,
            "District": "滨江区",
            "MOS_UL": 2.3,
            "color": 1,
            "slice_total_count": 177,
            "Cause_Radio_RSRP_DL_slice_num_rate": "0.0%",
            "Cause_Radio_RSRQ_UL_slice_num_rate": "0.0%",
            "End_Time": "2021-03-23 23:59:59",
            "Worse_Quality_slice_count_DL": 77,
            "pci": 490,
            "cause_ul_dl_unbalance_slice_num_rate": "0.0%",
            "radio_problem_slice_num_rate": "0.0%",
            "single_pass_call_num": 0,
            "rtp_packet_loss_num_DL_rate": "56.2%",
            "cause_neighbour_cell_loss_slice_num_rate": "0.0%",
            "Cause_Radio_RSRP_UL_slice_num_rate": "0.0%",
            "RTCP_ring_delay_UL": 11.6,
            "Worse_MOS_call_num_rate": "25.0%",
            "Cause_Radio_RSRQ_DL_slice_num_rate": "0.0%",
            "ECI": 53809613,
            "Call_Type": "全部",
            "cell_Name": "杭州吉利汽车大厦主楼19-21层SF_205",
            "Freq_band": "E1",
            "MOS_DL": 1.7,
            "RTCP_ring_delay_DL": 10.5,
            "radio_problem_mr_num": 0,
            "cause_overlap_coverage_slice_num_rate": "0.0%",
            "radio_problem_slice_num": 0
        }, {
            "cause_step_1_num_ul_rate": "11.1%",
            "Location_latitude": 30.229179,
            "single_pass_call_num_rate": "0.0%",
            "Worse_Quality_call_num_rate": "25.0%",
            "cause_step_1_num_dl_rate": "25.0%",
            "Worse_Quality_time_rate_DL": "27.2%",
            "slice_total_count_UL": 38,
            "local_city": "杭州",
            "Worse_Quality_call_num": 1,
            "Worse_MOS_call_num": 0,
            "Worse_Quality_time_rate_UL": "60.7%",
            "Worse_Quality_time_rate": "60.7%",
            "slice_total_count_DL": 38,
            "call_num": 4,
            "Worse_Quality_time": 135.0370000000000000,
            "call_time": 222.5320000000000000,
            "Worse_Quality_slice_count_UL": 27,
            "cause_null_main_coverage_slice_num_rate": "0.0%",
            "cause_mod3_conflict_slice_num_rate": "0.0%",
            "Start_Time": "2021-03-17 00:00:00",
            "rtp_packet_loss_num_UL_rate": "0.0%",
            "Location_longitude": 120.153376,
            "Freq": 38950,
            "Worse_Quality_slice_count": 39,
            "District": "上城区",
            "MOS_UL": 4.0,
            "color": 1,
            "slice_total_count": 76,
            "Cause_Radio_RSRP_DL_slice_num_rate": "0.0%",
            "Cause_Radio_RSRQ_UL_slice_num_rate": "0.0%",
            "End_Time": "2021-03-23 23:59:59",
            "Worse_Quality_slice_count_DL": 12,
            "pci": 141,
            "cause_ul_dl_unbalance_slice_num_rate": "0.0%",
            "radio_problem_slice_num_rate": "0.0%",
            "single_pass_call_num": 0,
            "rtp_packet_loss_num_DL_rate": "0.0%",
            "cause_neighbour_cell_loss_slice_num_rate": "0.0%",
            "Cause_Radio_RSRP_UL_slice_num_rate": "0.0%",
            "RTCP_ring_delay_UL": 96.9,
            "Worse_MOS_call_num_rate": "0.0%",
            "Cause_Radio_RSRQ_DL_slice_num_rate": "0.0%",
            "ECI": 155424389,
            "Call_Type": "全部",
            "cell_Name": "杭州师范大学音乐学院10号11号12号宿舍楼SF_133",
            "Freq_band": "E1",
            "MOS_DL": 4.0,
            "RTCP_ring_delay_DL": 95.8,
            "radio_problem_mr_num": 0,
            "cause_overlap_coverage_slice_num_rate": "0.0%",
            "radio_problem_slice_num": 0
        }, {
            "cause_step_1_num_ul_rate": null,
            "Location_latitude": 30.174167,
            "single_pass_call_num_rate": "0.0%",
            "Worse_Quality_call_num_rate": "33.3%",
            "cause_step_1_num_dl_rate": "0.0%",
            "Worse_Quality_time_rate_DL": "60.8%",
            "slice_total_count_UL": 11,
            "local_city": "杭州",
            "Worse_Quality_call_num": 1,
            "Worse_MOS_call_num": 1,
            "Worse_Quality_time_rate_UL": "0.0%",
            "Worse_Quality_time_rate": "59.1%",
            "slice_total_count_DL": 10,
            "call_num": 3,
            "Worse_Quality_time": 66.7790000000000000,
            "call_time": 113.0590000000000000,
            "Worse_Quality_slice_count_UL": 0,
            "cause_null_main_coverage_slice_num_rate": "0.0%",
            "cause_mod3_conflict_slice_num_rate": "0.0%",
            "Start_Time": "2021-03-16 00:00:00",
            "rtp_packet_loss_num_UL_rate": "0.0%",
            "Location_longitude": 120.152279,
            "Freq": 38950,
            "Worse_Quality_slice_count": 6,
            "District": "滨江区",
            "MOS_UL": 3.7,
            "color": 1,
            "slice_total_count": 21,
            "Cause_Radio_RSRP_DL_slice_num_rate": "0.0%",
            "Cause_Radio_RSRQ_UL_slice_num_rate": "0.0%",
            "End_Time": "2021-03-18 23:59:59",
            "Worse_Quality_slice_count_DL": 6,
            "pci": 184,
            "cause_ul_dl_unbalance_slice_num_rate": "0.0%",
            "radio_problem_slice_num_rate": "0.0%",
            "single_pass_call_num": 0,
            "rtp_packet_loss_num_DL_rate": "51.2%",
            "cause_neighbour_cell_loss_slice_num_rate": "0.0%",
            "Cause_Radio_RSRP_UL_slice_num_rate": "0.0%",
            "RTCP_ring_delay_UL": 7.2,
            "Worse_MOS_call_num_rate": "33.3%",
            "Cause_Radio_RSRQ_DL_slice_num_rate": "0.0%",
            "ECI": 100968705,
            "Call_Type": "全部",
            "cell_Name": "杭州立业园2号楼西侧SF_1",
            "Freq_band": "E1",
            "MOS_DL": 2.6,
            "RTCP_ring_delay_DL": 4.0,
            "radio_problem_mr_num": 0,
            "cause_overlap_coverage_slice_num_rate": "0.0%",
            "radio_problem_slice_num": 0
        }]
    },
    "status": "success",
    "msg": "查询成功"
}